{
  "id": "hotels_amami-island",
  "url": "https://ritotabi.com/hotels/amami-island/",
  "evaluatedAt": "2026-04-15",
  "evaluatedBy": "skill",
  "stream": "jp_amami",
  "sum": "21,500",
  "ap": "896",
  "an": "0",
  "ao": "2,100",
  "pp": [0, 45, 70, 120, 180, 280, 750, 850, 400, 750, 650, 820, 580, 680, 1150, 1250, 1850, 1100, 2100, 1950, 850, 1400, 1150, 1280],
  "pn": [0, 20, 35, 60, 90, 140, 380, 420, 200, 380, 320, 410, 290, 340, 580, 620, 920, 550, 1050, 980, 420, 700, 580, 640],
  "po": [0, 75, 120, 200, 320, 480, 1150, 1300, 750, 1250, 1100, 1400, 1000, 1150, 1950, 2100, 3100, 1850, 3500, 3300, 1450, 2350, 1950, 2150],
  "memo": "実走調査に基づく圧倒的な情報量が特徴。特に各ホテルの「Runner's Review」は、周辺のランニング環境や設備（ランドリー等）にまで踏み込んだ一次情報であり、他サイトにはない強い差別化要因となっている。エリア分類も「名瀬」「北部」と明確で、ユーザーの目的に即した宿選びを強力にサポートしている。",
  "quality": {
    "title": "奄美大島ホテルの真実｜北部・南部エリア別徹底比較 | RITOTABI",
    "lang": "JP",
    "type": "ホテル",
    "overall": 94,
    "publishedDate": "2026-02-18",
    "scores": {
      "コンテンツ独自性": 95,
      "写真・ビジュアル": 88,
      "アフィリエイト設計": 85,
      "内部リンク": 90,
      "SEO技術実装": 95,
      "ユーザー体験(UX)": 92
    },
    "seoChecklist": {
      "hreflang": true,
      "faq": true,
      "keyword": true,
      "meta": true,
      "canonical": true,
      "ogp": true
    },
    "freshness": "growing",
    "affiliateChecklist": {
      "ctaPosition": true,
      "microCopy": true,
      "multipleOta": false,
      "priceVisible": true,
      "socialProof": true,
      "mobileStickyCta": true,
      "carRentalLink": false,
      "activityLink": false,
      "urgencySignals": 1,
      "minClicks": 1
    },
    "brandChecklist": {
      "toneAndManner": true,
      "firstPersonInsight": true,
      "benefitUpfront": true,
      "personaDrivenPros": true
    },
    "categoryChecklist": {
      "comparisonTable": true,
      "affiliateMicroCopy": true,
      "courseSpecs": null,
      "runBadge": null
    },
    "techChecklist": {
      "nextImage": true,
      "imageAlt": true,
      "affiliateRel": true
    },
    "strengths": [
      "全ホテルにランナー視点での詳細な一次情報（Runner's Review）が付帯している",
      "「サウナ付き大浴場」や「ランドリー台数」など、宿泊者が本当に知りたい実用情報を網羅",
      "エリア別比較により、島内での位置関係と利便性が一目で理解できる構成",
      "マイクロコピーを活用した自然なアフィリエイト導線設計"
    ],
    "issues": [
      { "level": "中", "text": "アフィリエイトリンクが楽天トラベルのみとなっており、じゃらんやAgoda等を好むユーザーの離脱リスクがある。" },
      { "level": "低", "text": "レンタカー予約への導線がなく、ホテル選びとセットで必要になる移動手段の解決がページ内で完結していない。" }
    ]
  }
}
